pipeline/add_1.v
`timescale 1ns/1ps

module add_1(cout,sum,a,b,cin);

output cout;
output sum;

input a;
input b;
input cin;

wire w1;
wire w2;
wire w3;

xor g1 (sum,a,b,cin);
xor g2 (w1,a,b);
and g3 (w2,a,b);
and g4 (w3,w1,cin);
or g5 (cout,w2,w3);

endmodule

SEQ/add_1_tb.v
`timescale 1ns/1ps

module add_1_tb;

reg a;
reg b;
reg cin;
wire cout;
wire sum;

integer i;

add_1 m1 (cout,sum,a,b,cin);

initial
     begin
         $dumpfile("add_1.vcd");
         $dumpvars(0,add_1_tb);
         for(i=0;i<=7;i=i+1)begin
             {a,b,cin}=i;
             #5;
            $monitor("T = %2d a=%b, b=%b, c=%b, sum=%b cout=%b",$time,a,b,cin,sum,cout);
            #5;
         end
    #5 $finish;
     end
endmodule

SEQ/add_1.vcd
$date
	Thu Jan 27 20:38:00 2022
$end
$version
	Icarus Verilog
$end
$timescale
	1ps
$end
$scope module add_1_tb $end
$var wire 1 ! sum $end
$var wire 1 " cout $end
$var reg 1 # a $end
$var reg 1 $ b $end
$var reg 1 % cin $end
$var integer 32 & i [31:0] $end
$scope module m1 $end
$var wire 1 # a $end
$var wire 1 $ b $end
$var wire 1 % cin $end
$var wire 1 " cout $end
$var wire 1 ! sum $end
$var wire 1 ' w1 $end
$var wire 1 ( w2 $end
$var wire 1 ) w3 $end
$upscope $end
$upscope $end
$enddefinitions $end
#0
$dumpvars
0)
0(
0'
b0 &
0%
0$
0#
0"
0!
$end
#10000
1!
1%
b1 &
#20000
1'
1$
0%
b10 &
#30000
1"
0!
1)
1%
b11 &
#40000
0"
1!
0)
1#
0$
0%
b100 &
#50000
1"
0!
1)
1%
b101 &
#60000
0'
1(
0)
1$
0%
b110 &
#70000
1!
1%
b111 &
#80000
b1000 &
