SEQ/and_64.v
`timescale 1ns/1ps

module and_64(ans,a,b);

input signed [63:0] a;
input signed [63:0] b;

output signed [63:0] ans;


genvar i;

generate for(i=0;i<=63;i=i+1)
begin
    
    and g1 (ans[i],a[i],b[i]); 

end
endgenerate

endmodule

SEQ/and_64_tb.v
`timescale 1ns/1ps

module and_64_tb;

reg signed [63:0] a;
reg signed [63:0] b;

wire signed [63:0] ans;

and_64 m1 (ans,a,b);

initial 
   begin

        $dumpfile("and_64.vcd");
        $dumpvars(0,and_64_tb);
        a = 64'b0;
        b = 64'b0;
        #20;
        #5 a = 64'd100000000000000000; b = 64'd110101010101010101;
        #5 a = -64'd100000000000000000; b = 64'd110101010101010101;
        #5 a = 64'd100000000000000000; b = -64'd110101010101010101;
        #5 a = -64'd100000000000000000; b = -64'd110101010101010101;
        #5 a = 64'd20; b = 64'd50;
        #5 a = -64'd20; b = 64'd50;
        #5 a = 64'd20; b = -64'd50;
        #5 a = -64'd20; b = -64'd50;
   end

   initial

          $monitor("T = %2d and=%b, a=%b, b=%b",$time,ans,a,b); 
  
endmodule

SEQ/and_64.vcd
$date
	Fri Jan 28 10:41:03 2022
$end
$version
	Icarus Verilog
$end
$timescale
	1ps
$end
$scope module and_64_tb $end
$var wire 64 ! ans [63:0] $end
$var reg 64 " a [63:0] $end
$var reg 64 # b [63:0] $end
$scope module m1 $end
$var wire 64 $ a [63:0] $end
$var wire 64 % b [63:0] $end
$var wire 64 & ans [63:0] $end
$scope begin genblk1[0] $end
$upscope $end
$scope begin genblk1[1] $end
$upscope $end
$scope begin genblk1[2] $end
$upscope $end
$scope begin genblk1[3] $end
$upscope $end
$scope begin genblk1[4] $end
$upscope $end
$scope begin genblk1[5] $end
$upscope $end
$scope begin genblk1[6] $end
$upscope $end
$scope begin genblk1[7] $end
$upscope $end
$scope begin genblk1[8] $end
$upscope $end
$scope begin genblk1[9] $end
$upscope $end
$scope begin genblk1[10] $end
$upscope $end
$scope begin genblk1[11] $end
$upscope $end
$scope begin genblk1[12] $end
$upscope $end
$scope begin genblk1[13] $end
$upscope $end
$scope begin genblk1[14] $end
$upscope $end
$scope begin genblk1[15] $end
$upscope $end
$scope begin genblk1[16] $end
$upscope $end
$scope begin genblk1[17] $end
$upscope $end
$scope begin genblk1[18] $end
$upscope $end
$scope begin genblk1[19] $end
$upscope $end
$scope begin genblk1[20] $end
$upscope $end
$scope begin genblk1[21] $end
$upscope $end
$scope begin genblk1[22] $end
$upscope $end
$scope begin genblk1[23] $end
$upscope $end
$scope begin genblk1[24] $end
$upscope $end
$scope begin genblk1[25] $end
$upscope $end
$scope begin genblk1[26] $end
$upscope $end
$scope begin genblk1[27] $end
$upscope $end
$scope begin genblk1[28] $end
$upscope $end
$scope begin genblk1[29] $end
$upscope $end
$scope begin genblk1[30] $end
$upscope $end
$scope begin genblk1[31] $end
$upscope $end
$scope begin genblk1[32] $end
$upscope $end
$scope begin genblk1[33] $end
$upscope $end
$scope begin genblk1[34] $end
$upscope $end
$scope begin genblk1[35] $end
$upscope $end
$scope begin genblk1[36] $end
$upscope $end
$scope begin genblk1[37] $end
$upscope $end
$scope begin genblk1[38] $end
$upscope $end
$scope begin genblk1[39] $end
$upscope $end
$scope begin genblk1[40] $end
$upscope $end
$scope begin genblk1[41] $end
$upscope $end
$scope begin genblk1[42] $end
$upscope $end
$scope begin genblk1[43] $end
$upscope $end
$scope begin genblk1[44] $end
$upscope $end
$scope begin genblk1[45] $end
$upscope $end
$scope begin genblk1[46] $end
$upscope $end
$scope begin genblk1[47] $end
$upscope $end
$scope begin genblk1[48] $end
$upscope $end
$scope begin genblk1[49] $end
$upscope $end
$scope begin genblk1[50] $end
$upscope $end
$scope begin genblk1[51] $end
$upscope $end
$scope begin genblk1[52] $end
$upscope $end
$scope begin genblk1[53] $end
$upscope $end
$scope begin genblk1[54] $end
$upscope $end
$scope begin genblk1[55] $end
$upscope $end
$scope begin genblk1[56] $end
$upscope $end
$scope begin genblk1[57] $end
$upscope $end
$scope begin genblk1[58] $end
$upscope $end
$scope begin genblk1[59] $end
$upscope $end
$scope begin genblk1[60] $end
$upscope $end
$scope begin genblk1[61] $end
$upscope $end
$scope begin genblk1[62] $end
$upscope $end
$scope begin genblk1[63] $end
$upscope $end
$upscope $end
$upscope $end
$enddefinitions $end
#0
$dumpvars
b0 &
b0 %
b0 $
b0 #
b0 "
b0 !
$end
#25000
b100000011000000000100100000001100000010100000000000000000 !
b100000011000000000100100000001100000010100000000000000000 &
b110000111001010000100100100001100011110110111111010110101 #
b110000111001010000100100100001100011110110111111010110101 %
b101100011010001010111100001011101100010100000000000000000 "
b101100011010001010111100001011101100010100000000000000000 $
#30000
b10000100001010000000000100000000011100100000000000000000 !
b10000100001010000000000100000000011100100000000000000000 &
b1111111010011100101110101000011110100010011101100000000000000000 "
b1111111010011100101110101000011110100010011101100000000000000000 $
#35000
b1100000010001010011000001010001100000000000000000000000 !
b1100000010001010011000001010001100000000000000000000000 &
b1111111001111000110101111011011011110011100001001000000101001011 #
b1111111001111000110101111011011011110011100001001000000101001011 %
b101100011010001010111100001011101100010100000000000000000 "
b101100011010001010111100001011101100010100000000000000000 $
#40000
b1111111000011000100100101000011010100010000001000000000000000000 !
b1111111000011000100100101000011010100010000001000000000000000000 &
b1111111010011100101110101000011110100010011101100000000000000000 "
b1111111010011100101110101000011110100010011101100000000000000000 $
#45000
b10000 !
b10000 &
b110010 #
b110010 %
b10100 "
b10100 $
#50000
b100000 !
b100000 &
b1111111111111111111111111111111111111111111111111111111111101100 "
b1111111111111111111111111111111111111111111111111111111111101100 $
#55000
b100 !
b100 &
b1111111111111111111111111111111111111111111111111111111111001110 #
b1111111111111111111111111111111111111111111111111111111111001110 %
b10100 "
b10100 $
#60000
b1111111111111111111111111111111111111111111111111111111111001100 !
b1111111111111111111111111111111111111111111111111111111111001100 &
b1111111111111111111111111111111111111111111111111111111111101100 "
b1111111111111111111111111111111111111111111111111111111111101100 $
